jupyter_ai_chatgpt/__init__.py
jupyter_ai_chatgpt/_version.py
jupyter_ai_chatgpt/engine.py
jupyter_ai_chatgpt/tests/__init__.py
jupyter_ai_chatgpt-0.4.0.data/data/share/jupyter/labextensions/@jupyter-ai/chatgpt/package.json
jupyter_ai_chatgpt-0.4.0.data/data/share/jupyter/labextensions/@jupyter-ai/chatgpt/static/568.58d646ba30ad5cce43b0.js
jupyter_ai_chatgpt-0.4.0.data/data/share/jupyter/labextensions/@jupyter-ai/chatgpt/static/643.c1827be98afe184c4f03.js
jupyter_ai_chatgpt-0.4.0.data/data/share/jupyter/labextensions/@jupyter-ai/chatgpt/static/remoteEntry.ec582f0e83f6f33ab335.js
jupyter_ai_chatgpt-0.4.0.data/data/share/jupyter/labextensions/@jupyter-ai/chatgpt/static/style.js
jupyter_ai_chatgpt-0.4.0.data/data/share/jupyter/labextensions/@jupyter-ai/chatgpt/static/third-party-licenses.json
jupyter_ai_chatgpt-0.4.0.data/data/share/jupyter/labextensions/@jupyter-ai/chatgpt/install.json
jupyter_ai_chatgpt-0.4.0.dist-info/METADATA
jupyter_ai_chatgpt-0.4.0.dist-info/WHEEL
jupyter_ai_chatgpt-0.4.0.dist-info/entry_points.txt
jupyter_ai_chatgpt-0.4.0.dist-info/licenses/LICENSE
jupyter_ai_chatgpt-0.4.0.dist-info/RECORD
