Metadata-Version: 2.1
Name: jupyter_ai_chatgpt
Version: 0.4.0
Summary: Jupyter AI module that provides a ChatGPT model engine.
Project-URL: Homepage, https://github.com/jupyterlab/jupyter-ai
Project-URL: Bug Tracker, https://github.com/jupyterlab/jupyter-ai/issues
Project-URL: Repository, https://github.com/jupyterlab/jupyter-ai.git
Author-email: Project Jupyter <jupyter@googlegroups.com>
License: BSD 3-Clause License
License-File: LICENSE
Classifier: Framework :: Jupyter
Classifier: Framework :: Jupyter :: JupyterLab
Classifier: Framework :: Jupyter :: JupyterLab :: 3
Classifier: Framework :: Jupyter :: JupyterLab :: Extensions
Classifier: Framework :: Jupyter :: JupyterLab :: Extensions :: Prebuilt
Classifier: License :: OSI Approved :: BSD License
Classifier: Programming Language :: Python
Classifier: Programming Language :: Python :: 3
Classifier: Programming Language :: Python :: 3.7
Classifier: Programming Language :: Python :: 3.8
Classifier: Programming Language :: Python :: 3.9
Classifier: Programming Language :: Python :: 3.10
Classifier: Programming Language :: Python :: 3.11
Requires-Python: >=3.7
Requires-Dist: jupyter-ai
Provides-Extra: test
Requires-Dist: coverage; extra == 'test'
Requires-Dist: pytest; extra == 'test'
Requires-Dist: pytest-asyncio; extra == 'test'
Requires-Dist: pytest-cov; extra == 'test'
